{"entities":{"Q6283079":{"type":"item","id":"Q6283079","labels":{"en":{"language":"en","value":"Joseph Fielding Smith"}},"claims":{"P214":[{"mainsnak":{"snaktype":"value","property":"P214","hash":"93ab936202fab67a4459bbb3406bbeb80339003d","datavalue":{"value":"24206981","type":"string"},"datatype":"external-id"},"type":"statement","id":"q6283079$92C40B46-DE70-4082-8C84-5C7A11E07CB1","rank":"normal","references":[{"hash":"fa278ebfc458360e5aed63d5058cca83c46134f1","snaks":{"P143":[{"snaktype":"value","property":"P143","hash":"e4f6d9441d0600513c4533c672b5ab472dc73694","datavalue":{"value":{"entity-type":"item","numeric-id":328,"id":"Q328"},"type":"wikibase-entityid"},"datatype":"wikibase-item"}]},"snaks-order":["P143"]}]}],"P21":[{"mainsnak":{"snaktype":"value","property":"P21","hash":"85ad4b1c7348f7a5aac521135040d74e91fb5939","datavalue":{"value":{"entity-type":"item","numeric-id":6581097,"id":"Q6581097"},"type":"wikibase-entityid"},"datatype":"wikibase-item"},"type":"statement","id":"q6283079$FAD6CD52-4AE3-490A-B5DF-56191B4F6EC6","rank":"normal"}],"P31":[{"mainsnak":{"snaktype":"value","property":"P31","hash":"ad7d38a03cdd40cdc373de0dc4e7b7fcbccb31d9","datavalue":{"value":{"entity-type":"item","numeric-id":5,"id":"Q5"},"type":"wikibase-entityid"},"datatype":"wikibase-item"},"type":"statement","id":"Q6283079$DCC20B8C-3CF2-420B-B0BD-8B84E2765D13","rank":"normal","references":[{"hash":"fa278ebfc458360e5aed63d5058cca83c46134f1","snaks":{"P143":[{"snaktype":"value","property":"P143","hash":"e4f6d9441d0600513c4533c672b5ab472dc73694","datavalue":{"value":{"entity-type":"item","numeric-id":328,"id":"Q328"},"type":"wikibase-entityid"},"datatype":"wikibase-item"}]},"snaks-order":["P143"]}]}],"P570":[{"mainsnak":{"snaktype":"value","property":"P570","hash":"36ba899bac32767fc07777482923285fb30af5af","datavalue":{"value":{"time":"+1964-08-29T00:00:00Z","timezone":0,"before":0,"after":0,"precision":11,"calendarmodel":"http://www.wikidata.org/entity/Q1985727"},"type":"time"},"datatype":"time"},"type":"statement","id":"Q6283079$2EBA7871-49DC-4444-B254-50036D2A6FF9","rank":"normal","references":[{"hash":"fa278ebfc458360e5aed63d5058cca83c46134f1","snaks":{"P143":[{"snaktype":"value","property":"P143","hash":"e4f6d9441d0600513c4533c672b5ab472dc73694","datavalue":{"value":{"entity-type":"item","numeric-id":328,"id":"Q328"},"type":"wikibase-entityid"},"datatype":"wikibase-item"}]},"snaks-order":["P143"]}]}],"P735":[{"mainsnak":{"snaktype":"value","property":"P735","hash":"ec3c4d703def6a4dd387201c8b28ef51639ea4be","datavalue":{"value":{"entity-type":"item","numeric-id":471788,"id":"Q471788"},"type":"wikibase-entityid"},"datatype":"wikibase-item"},"type":"statement","id":"Q6283079$3DC0F5F0-821B-4FD6-8ACE-9E6AF2FD7477","rank":"normal"}],"P69":[{"mainsnak":{"snaktype":"value","property":"P69","hash":"e6975a5807bf6098a23db2cc7bf476131520a473","datavalue":{"value":{"entity-type":"item","numeric-id":168515,"id":"Q168515"},"type":"wikibase-entityid"},"datatype":"wikibase-item"},"type":"statement","id":"Q6283079$0E275B7B-5B96-4F40-A0B8-31F060478384","rank":"normal"}],"P569":[{"mainsnak":{"snaktype":"value","property":"P569","hash":"c74ab6fcf4c1d0ef73a0d8db54b114b4e8aa0a8c","datavalue":{"value":{"time":"+1899-01-30T00:00:00Z","timezone":0,"before":0,"after":0,"precision":11,"calendarmodel":"http://www.wikidata.org/entity/Q1985727"},"type":"time"},"datatype":"time"},"type":"statement","id":"Q6283079$816F1B04-CD50-4ADC-B125-00978EF10D0A","rank":"normal"}],"P18":[{"mainsnak":{"snaktype":"value","property":"P18","hash":"06326c62e62005e92aaa25238ae51f922788018b","datavalue":{"value":"Joseph Fielding Smith (presiding patriarch).jpg","type":"string"},"datatype":"commonsMedia"},"type":"statement","id":"Q6283079$252EE205-4F72-4749-985B-E12AAECD8665","rank":"normal"}],"P734":[{"mainsnak":{"snaktype":"value","property":"P734","hash":"b7ba21c1c5b64a234b839a8871e17e64763c1c4a","datavalue":{"value":{"entity-type":"item","numeric-id":1158446,"id":"Q1158446"},"type":"wikibase-entityid"},"datatype":"wikibase-item"},"type":"statement","id":"Q6283079$7BED2A57-6604-4A3B-AB92-CEA5D8FAC3A9","rank":"normal"}],"P19":[{"mainsnak":{"snaktype":"value","property":"P19","hash":"b266c07b3e4beb5811aac4ab2f56c0a67d0f53c0","datavalue":{"value":{"entity-type":"item","numeric-id":23337,"id":"Q23337"},"type":"wikibase-entityid"},"datatype":"wikibase-item"},"type":"statement","id":"Q6283079$6314CBEC-A410-4AC6-A025-CF7EA14D68CE","rank":"normal","references":[{"hash":"fa278ebfc458360e5aed63d5058cca83c46134f1","snaks":{"P143":[{"snaktype":"value","property":"P143","hash":"e4f6d9441d0600513c4533c672b5ab472dc73694","datavalue":{"value":{"entity-type":"item","numeric-id":328,"id":"Q328"},"type":"wikibase-entityid"},"datatype":"wikibase-item"}]},"snaks-order":["P143"]}]}],"P20":[{"mainsnak":{"snaktype":"value","property":"P20","hash":"9315f2edc5dd968f5a56e966bcb0c3984d9a7673","datavalue":{"value":{"entity-type":"item","numeric-id":23337,"id":"Q23337"},"type":"wikibase-entityid"},"datatype":"wikibase-item"},"type":"statement","id":"Q6283079$8859152E-777E-418E-8258-1D3F5D626561","rank":"normal","references":[{"hash":"fa278ebfc458360e5aed63d5058cca83c46134f1","snaks":{"P143":[{"snaktype":"value","property":"P143","hash":"e4f6d9441d0600513c4533c672b5ab472dc73694","datavalue":{"value":{"entity-type":"item","numeric-id":328,"id":"Q328"},"type":"wikibase-entityid"},"datatype":"wikibase-item"}]},"snaks-order":["P143"]}]}],"P244":[{"mainsnak":{"snaktype":"value","property":"P244","hash":"56d9f7e678efe659ba4148c025b60fd7b5c9eb30","datavalue":{"value":"no97047473","type":"string"},"datatype":"external-id"},"type":"statement","id":"Q6283079$C8196F3E-25EB-495B-B9B8-CAB06E4CCBD3","rank":"normal","references":[{"hash":"5ddef883d3b105f6279c9b4191d2e5d69b97d863","snaks":{"P214":[{"snaktype":"value","property":"P214","hash":"93ab936202fab67a4459bbb3406bbeb80339003d","datavalue":{"value":"24206981","type":"string"},"datatype":"external-id"}],"P813":[{"snaktype":"value","property":"P813","hash":"90b07ccbc53e001d2d08416c7bcb6e9977dad247","datavalue":{"value":{"time":"+2017-10-20T00:00:00Z","timezone":0,"before":0,"after":0,"precision":11,"calendarmodel":"http://www.wikidata.org/entity/Q1985727"},"type":"time"},"datatype":"time"}],"P248":[{"snaktype":"value","property":"P248","hash":"6b7d4330c4aac4caec4ede9de0311ce273f88ecd","datavalue":{"value":{"entity-type":"item","numeric-id":54919,"id":"Q54919"},"type":"wikibase-entityid"},"datatype":"wikibase-item"}]},"snaks-order":["P214","P813","P248"]}]}],"P2163":[{"mainsnak":{"snaktype":"value","property":"P2163","hash":"8bb193568f16021cd5a7380544cad077395fae27","datavalue":{"value":"1989627","type":"string"},"datatype":"external-id"},"type":"statement","id":"Q6283079$7EB83929-EF9C-4E3F-8DA8-FA311E4312EA","rank":"normal","references":[{"hash":"ca09423f475b5d073399a7475a9f3870dfe0c8b1","snaks":{"P244":[{"snaktype":"value","property":"P244","hash":"56d9f7e678efe659ba4148c025b60fd7b5c9eb30","datavalue":{"value":"no97047473","type":"string"},"datatype":"external-id"}],"P248":[{"snaktype":"value","property":"P248","hash":"c120f07504c77593a9d734f50361ea829f601960","datavalue":{"value":{"entity-type":"item","numeric-id":620946,"id":"Q620946"},"type":"wikibase-entityid"},"datatype":"wikibase-item"}],"P813":[{"snaktype":"value","property":"P813","hash":"0cd0399e778f66d514abac5cd6109335d422e78a","datavalue":{"value":{"time":"+2020-03-25T00:00:00Z","timezone":0,"before":0,"after":0,"precision":11,"calendarmodel":"http://www.wikidata.org/entity/Q1985727"},"type":"time"},"datatype":"time"}]},"snaks-order":["P244","P248","P813"]}]}],"P1207":[{"mainsnak":{"snaktype":"value","property":"P1207","hash":"4431183d79643fa76d13b1aa235e875663d243b7","datavalue":{"value":"n2020020736","type":"string"},"datatype":"external-id"},"type":"statement","id":"Q6283079$03078224-D4D1-465B-8907-0CC7CC383641","rank":"normal","references":[{"hash":"2bfea46dcb8a6ef4c07bf7a2428963b695aadb9b","snaks":{"P214":[{"snaktype":"value","property":"P214","hash":"93ab936202fab67a4459bbb3406bbeb80339003d","datavalue":{"value":"24206981","type":"string"},"datatype":"external-id"}],"P248":[{"snaktype":"value","property":"P248","hash":"6b7d4330c4aac4caec4ede9de0311ce273f88ecd","datavalue":{"value":{"entity-type":"item","numeric-id":54919,"id":"Q54919"},"type":"wikibase-entityid"},"datatype":"wikibase-item"}],"P813":[{"snaktype":"value","property":"P813","hash":"c6d714f29789c53e503768097d201d5277a3a568","datavalue":{"value":{"time":"+2020-09-02T00:00:00Z","timezone":0,"before":0,"after":0,"precision":11,"calendarmodel":"http://www.wikidata.org/entity/Q1985727"},"type":"time"},"datatype":"time"}]},"snaks-order":["P214","P248","P813"]}]}],"P646":[{"mainsnak":{"snaktype":"value","property":"P646","hash":"9e19e6c95e82027d8556497bc217729833dc5bd2","datavalue":{"value":"/m/027lwyn","type":"string"},"datatype":"external-id"},"type":"statement","id":"Q6283079$7668C82C-F2FC-4CAD-AF11-ADACA409DAD5","rank":"normal"}],"P3368":[{"mainsnak":{"snaktype":"value","property":"P3368","hash":"e70e0e8585f33f737c0883c0042b5937d6fc084c","datavalue":{"value":"2247357","type":"string"},"datatype":"external-id"},"type":"statement","id":"Q6283079$2611B38A-17A0-4FFF-A68D-64430AD2D9F1","rank":"normal"}],"P10832":[{"mainsnak":{"snaktype":"value","property":"P10832","hash":"f25492546773dc29f8b7f0e4b59f431736038a8c","datavalue":{"value":"E39PBJkMMQXwhT8hGQRQJW3WjC","type":"string"},"datatype":"external-id"},"type":"statement","id":"Q6283079$98FF3467-D7C1-4488-AAC7-37AA6365FBD9","rank":"normal","references":[{"hash":"fa5f79037132727d7a3aa8a27feea269f89fbcae","snaks":{"P11797":[{"snaktype":"value","property":"P11797","hash":"ebc61ebee105944aa63ee48264c820fab36c5571","datavalue":{"value":{"entity-type":"item","numeric-id":13219454,"id":"Q13219454"},"type":"wikibase-entityid"},"datatype":"wikibase-item"}],"P244":[{"snaktype":"value","property":"P244","hash":"56d9f7e678efe659ba4148c025b60fd7b5c9eb30","datavalue":{"value":"no97047473","type":"string"},"datatype":"external-id"}],"P813":[{"snaktype":"value","property":"P813","hash":"b24aca38f0b7c8ead1687722b7dad83a5070d097","datavalue":{"value":{"time":"+2024-04-16T00:00:00Z","timezone":0,"before":0,"after":0,"precision":11,"calendarmodel":"http://www.wikidata.org/entity/Q1985727"},"type":"time"},"datatype":"time"}]},"snaks-order":["P11797","P244","P813"]}]}],"P13591":[{"mainsnak":{"snaktype":"value","property":"P13591","hash":"4f09168030dfbbf1e4a1812b454baa6cbf7f3a9b","datavalue":{"value":"person/ab62f128-cbbb-42cb-8b2b-ed103d54163c","type":"string"},"datatype":"external-id"},"type":"statement","id":"Q6283079$60BDBE8F-D532-49FA-B86F-E550100900F0","rank":"normal"}],"P27":[{"mainsnak":{"snaktype":"value","property":"P27","hash":"52d0408c7915122e0519a22577f0cbdcb28f749b","datavalue":{"value":{"entity-type":"item","numeric-id":30,"id":"Q30"},"type":"wikibase-entityid"},"datatype":"wikibase-item"},"type":"statement","id":"Q6283079$3334518B-71C7-49EE-B2C4-D799E043A717","rank":"normal"}]}}},"success":1}