{"type":"standard","title":"Barbara W. Winder","displaytitle":"<span lang=\"en\" dir=\"ltr\"><span class=\"mw-page-title-main\">Barbara W. Winder</span></span>","namespace":{"id":0,"text":""},"wikibase_item":"Q4859382","titles":{"canonical":"Barbara_W._Winder","normalized":"Barbara W. Winder","display":"<span lang=\"en\" dir=\"ltr\"><span class=\"mw-page-title-main\">Barbara W. Winder</span></span>"},"pageid":12775642,"lang":"en","dir":"ltr","revision":"1293461586","tid":"ee2585a0-3f2d-11f0-84ac-7b09e514485e","timestamp":"2025-06-01T21:18:15Z","description":"American religious and charity leader (1931–2017)","description_source":"local","content_urls":{"desktop":{"page":"https://en.wikipedia.org/wiki/Barbara_W._Winder","revisions":"https://en.wikipedia.org/wiki/Barbara_W._Winder?action=history","edit":"https://en.wikipedia.org/wiki/Barbara_W._Winder?action=edit","talk":"https://en.wikipedia.org/wiki/Talk:Barbara_W._Winder"},"mobile":{"page":"https://en.wikipedia.org/wiki/Barbara_W._Winder","revisions":"https://en.wikipedia.org/wiki/Special:History/Barbara_W._Winder","edit":"https://en.wikipedia.org/wiki/Barbara_W._Winder?action=edit","talk":"https://en.wikipedia.org/wiki/Talk:Barbara_W._Winder"}},"extract":"Barbara Ann Woodhead Winder was the eleventh general president of the Relief Society of the Church of Jesus Christ of Latter-day Saints from 1984 to 1990.","extract_html":"<p><b>Barbara Ann Woodhead Winder</b> was the eleventh general president of the Relief Society of the Church of Jesus Christ of Latter-day Saints from 1984 to 1990.</p>"}